calculator/__init__.py
calculator/calculator.py
esivcalculator-1.0.0.dist-info/LICENSE
esivcalculator-1.0.0.dist-info/METADATA
esivcalculator-1.0.0.dist-info/WHEEL
esivcalculator-1.0.0.dist-info/top_level.txt
esivcalculator-1.0.0.dist-info/RECORD
